mdfft/__init__.py
mdfft/candle/__init__.py
mdfft/candle/candle.py
mdfft/candle/candles.py
mdfft/candle/pandas_candles.py
mdfft/fractal/__init__.py
mdfft/fractal/fractal.py
mdfft/fractal/fractal_line.py
mdfft/fractal/fractal_master.py
mdfft/painter/__init__.py
mdfft/painter/painter.py
mdfft/painter/styler.py
mdfft/parsers/__init__.py
mdfft/parsers/raw_candle.py
mdfft/parsers/simple_parser.py
mdfft/timeframe/__init__.py
mdfft/timeframe/timeframe.py
mdfft/trader/__init__.py
mdfft/trader/trader.py
mdfft-1.0.11.dist-info/METADATA
mdfft-1.0.11.dist-info/WHEEL
mdfft-1.0.11.dist-info/licenses/LICENSE
mdfft-1.0.11.dist-info/RECORD
