Metadata-Version: 2.4
Name: mdfft
Version: 1.0.11
Summary: Market Data Form Finder Toolkit (MDFFT). The project goal is to make working with a raw market data easier.
Project-URL: Homepage, https://github.com/shai-trading/mfft
Project-URL: Issues, https://github.com/shai-trading/mfft/issues
Author-email: Evan Shamal <puuxxx1@gmail.com>
License-File: LICENSE
Classifier: License :: OSI Approved :: MIT License
Classifier: Operating System :: OS Independent
Classifier: Programming Language :: Python :: 3
Requires-Python: >=3.8
Requires-Dist: matplotlib
Requires-Dist: numpy
Requires-Dist: pandas
Requires-Dist: pytz
Requires-Dist: tzlocal
